sphinx_comments_zhaojiedi/__init__.py
sphinx_comments_zhaojiedi-1.0.4.dist-info/licenses/LICENSE
sphinx_comments_zhaojiedi-1.0.4.dist-info/METADATA
sphinx_comments_zhaojiedi-1.0.4.dist-info/WHEEL
sphinx_comments_zhaojiedi-1.0.4.dist-info/top_level.txt
sphinx_comments_zhaojiedi-1.0.4.dist-info/RECORD
