Metadata-Version: 2.4
Name: sphinx-comments-zhaojiedi
Version: 1.0.4
Summary: Add comments and annotation to your documentation.
Home-page: https://github.com/executablebooks/sphinx-comments
Author: Executable Book Project
License: MIT License
Classifier: License :: OSI Approved :: MIT License
License-File: LICENSE
Requires-Dist: sphinx>=1.8
Provides-Extra: code-style
Requires-Dist: flake8<3.8.0,>=3.7.0; extra == "code-style"
Requires-Dist: black; extra == "code-style"
Requires-Dist: pre-commit==1.17.0; extra == "code-style"
Provides-Extra: sphinx
Requires-Dist: sphinx>=2; extra == "sphinx"
Requires-Dist: sphinx_book_theme; extra == "sphinx"
Requires-Dist: myst_parser; extra == "sphinx"
Provides-Extra: testing
Requires-Dist: beautifulsoup4; extra == "testing"
Requires-Dist: myst-parser; extra == "testing"
Requires-Dist: pytest; extra == "testing"
Requires-Dist: pytest-regressions; extra == "testing"
Requires-Dist: sphinx>=2; extra == "testing"
Requires-Dist: sphinx_book_theme; extra == "testing"
Requires-Dist: myst_parser; extra == "testing"
Dynamic: author
Dynamic: classifier
Dynamic: description
Dynamic: description-content-type
Dynamic: home-page
Dynamic: license
Dynamic: license-file
Dynamic: provides-extra
Dynamic: requires-dist
Dynamic: summary
